<?xml version="1.0" encoding="UTF-8"?>
<BeeTable xmlns="http://www.butent.com/table"

  name="ReminderTypes"
  idName="ReminderTypeID"
  >
  <BeeFields>
    <BeeField name="Name" type="STRING" precision="30" notNull="true" unique="true" />
    <BeeField name="Method" type="INTEGER" notNull="true" />

    <BeeField name="Hours" type="INTEGER" />
    <BeeField name="Minutes" type="INTEGER" />
    <BeeField name="Template" type="TEXT" />

    <BeeField name="Description" type="TEXT" />
  </BeeFields>
</BeeTable>
