<?xml version="1.0" encoding="UTF-8"?>
<Table xmlns="http://www.butent.com/table"

  name="Items"
  idName="ItemID"
  >
  <Fields>
    <String name="Name" precision="100" notNull="true" label="Pavadinimas" />
    <Relation name="Unit" notNull="true" relation="Units" />
    <String name="Article" precision="30" unique="true" label="Artikulas" />
    <String name="Barcode" precision="30" unique="true" label="Barkodas" />
    <Numeric name="Price" precision="15" scale="5" label="Pard.kaina" />
    <Relation name="Currency" relation="Currencies" />
    <Boolean name="IsService" />
  </Fields>
  <Keys>
    <Key>
      <KeyField>IsService</KeyField>
    </Key>
  </Keys>
</Table>
