<?xml version="1.0" encoding="UTF-8"?>
<!DOCTYPE Form [
  <!ENTITY lbl1 "width: 115px; text-align: right; padding-right: 9px;">
]>
<HorizontalPanel xmlns="http://www.butent.com/widget"
    xmlns:ui="http://www.butent.com/ui"
  >
  <Table style="border-spacing: 5px;">
    <row>
      <cell colSpan="2">
        <Label text="=loading" horizontalAlignment="center" style="font-weight: bold;" />
      </cell>
    </row>
    <row>
      <Label text="=date" horizontalAlignment="right" style="&lbl1;"/>
      <InputDateTime source="LoadingDate" style="width: 110px;" />
    </row>
    <row>
      <Label text="=note" horizontalAlignment="right" style="&lbl1;"/>
      <InputText source="LoadingNote" />
    </row>
    <row>
      <Label text="=company" horizontalAlignment="right" style="&lbl1;"/>
      <InputText source="LoadingCompany" autocompleteKey="cargo-place-company" />
    </row>
    <row>
      <Label text="=address" horizontalAlignment="right" style="&lbl1;"/>
      <InputText source="LoadingAddress" autocompleteKey="cargo-place-address" />
    </row>
    <row>
      <Label text="=city" horizontalAlignment="right" style="&lbl1;"/>
      <DataSelector source="LoadingCity" style="width: 155px;" options="LoadingCountry">
        <selectorColumn source="Name" />
        <selectorColumn source="CountryName" />
        <selectorColumn source="CountryCode">
          <ui:renderer type="flag" />
        </selectorColumn>
      </DataSelector>
    </row>
    <row>
      <Label text="=postIndex" horizontalAlignment="right" style="&lbl1;"/>
      <InputText source="LoadingPostIndex" style="width: 90px;" 
        autocompleteKey="cargo-place-postal-code" />
    </row>
    <row>
      <Label text="=country" horizontalAlignment="right" style="&lbl1;"/>
      <FlowPanel>
        <DataSelector source="LoadingCountry" style="width: 135px;" >
          <renderToken source="LoadingCountryName" />
          <renderToken source="LoadingCountryCode" prefix=" (" suffix=")" />
          <selectorColumn source="Name" />
          <selectorColumn source="Code">
            <ui:renderer type="flag" />
          </selectorColumn>
        </DataSelector>

        <Flag source="LoadingCountryCode" style="padding-left: 2px;" />
      </FlowPanel>
    </row>
    <row>
      <Label text="=personContact" horizontalAlignment="right" style="&lbl1;"/>
      <InputText source="LoadingContact" autocompleteKey="cargo-place-contact" />
    </row>
    <row>
      <Label text="=ref" horizontalAlignment="right" style="&lbl1;"/>
      <InputText source="LoadingNumber" />
    </row>
  </Table>

  <Table style="border-spacing: 5px;">
    <row>
      <cell colSpan="2">
        <Label text="=unloading" horizontalAlignment="center" style="font-weight: bold;" />
      </cell>
    </row>
    <row>
      <Label text="=date" horizontalAlignment="right" style="&lbl1;"/>
      <InputDateTime source="UnloadingDate" style="width: 110px;" />
    </row>
    <row>
      <Label text="=note" horizontalAlignment="right" style="&lbl1;"/>
      <InputText source="UnloadingNote" />
    </row>
    <row>
      <Label text="=company" horizontalAlignment="right" style="&lbl1;"/>
      <InputText source="UnloadingCompany" autocompleteKey="cargo-place-company" />
    </row>
   
    <row>
      <Label text="=address" horizontalAlignment="right" style="&lbl1;"/>
      <InputText source="UnloadingAddress" autocompleteKey="cargo-place-address" />
    </row>
    <row>
      <Label text="=city" horizontalAlignment="right" style="&lbl1;"/>
      <DataSelector source="UnloadingCity" style="width: 155px;" options="UnloadingCountry">
        <selectorColumn source="Name" />
        <selectorColumn source="CountryName" />
        <selectorColumn source="CountryCode">
          <ui:renderer type="flag" />
        </selectorColumn>
      </DataSelector>
    </row>
    <row>
      <Label text="=postIndex" horizontalAlignment="right" style="&lbl1;"/>
      <InputText source="UnloadingPostIndex" style="width: 90px;"
        autocompleteKey="cargo-place-postal-code" />
    </row>
    <row>
      <Label text="=country" horizontalAlignment="right" style="&lbl1;"/>
      <FlowPanel>
        <DataSelector source="UnloadingCountry" style="width: 135px;" >
          <renderToken source="UnloadingCountryName" />
          <renderToken source="UnloadingCountryCode" prefix=" (" suffix=")" />
          <selectorColumn source="Name" />
          <selectorColumn source="Code">
            <ui:renderer type="flag" />
          </selectorColumn>
        </DataSelector>

        <Flag source="UnloadingCountryCode" style="padding-left: 2px;" />
      </FlowPanel>
    </row>
    <row>
      <Label text="=personContact" horizontalAlignment="right" style="&lbl1;"/>
      <InputText source="UnloadingContact" autocompleteKey="cargo-place-contact" />
    </row>
    <row>
      <Label text="=ref" horizontalAlignment="right" style="&lbl1;"/>
      <InputText source="UnloadingNumber" />
    </row>
  </Table>
</HorizontalPanel>
